{
    "project_assessments": [
        {},
        {
            "project_id": 5342,
            "assessment_id": "01jp88a66vye03najah01qqp4z"
        },
        {
            "project_id": 5031,
            "assessment_id": "01jp88bsdg4kysnpczetdskvbb"
        },
        {
            "project_id": 30655,
            "assessment_id": "01jns7fm1cvrwp4zsy4bxxh6qe"
        },
        {
            "project_id": 5416,
            "assessment_id": "01jk8crcgzcsgk2kqs7p1acvgg"
        }
    ],
    "designs": {
        "5342": [
            {
                "name": "2",
                "installed_capacity_dc": 472.52484,
                "land_area": 1055131.1053458205,
                "energy_yield": 2.11233210101668
            },
            {
                "name": "3",
                "installed_capacity_dc": 455.03261999999995,
                "land_area": 1055131.1053458205,
                "energy_yield": 2.137792971512524
            },
            {
                "name": "4",
                "installed_capacity_dc": 490.01705999999996,
                "land_area": 1055131.1053458205,
                "energy_yield": 2.084042594254019
            },
            {
                "name": "5",
                "installed_capacity_dc": 437.5404,
                "land_area": 1055131.1053458205,
                "energy_yield": 2.1589369799790297
            },
            {
                "name": "6",
                "installed_capacity_dc": 507.50928,
                "land_area": 1055131.1053458205,
                "energy_yield": 2.0536914100436516
            },
            {
                "name": "7",
                "installed_capacity_dc": 525.0015,
                "land_area": 1055131.1053458205,
                "energy_yield": 2.0216216185582994
            },
            {
                "name": "8",
                "installed_capacity_dc": 472.52484,
                "land_area": 1047024.5733917955,
                "energy_yield": 2.089121913468755
            },
            {
                "name": "9",
                "installed_capacity_dc": 455.03261999999995,
                "land_area": 1047024.5733917955,
                "energy_yield": 2.1141393629037055
            },
            {
                "name": "10",
                "installed_capacity_dc": 490.01705999999996,
                "land_area": 1047024.5733917955,
                "energy_yield": 2.0611951704341402
            },
            {
                "name": "11",
                "installed_capacity_dc": 437.5404,
                "land_area": 1047024.5733917955,
                "energy_yield": 2.134726065477493
            },
            {
                "name": "12",
                "installed_capacity_dc": 507.50928,
                "land_area": 1047024.5733917955,
                "energy_yield": 2.0312474942385843
            },
            {
                "name": "13",
                "installed_capacity_dc": 525.0015,
                "land_area": 1047024.5733917955,
                "energy_yield": 1.9995706063454544
            },
            {
                "name": "14",
                "installed_capacity_dc": 472.52484,
                "land_area": 1036384.24183633,
                "energy_yield": 2.0611895969724254
            },
            {
                "name": "15",
                "installed_capacity_dc": 455.03261999999995,
                "land_area": 1036384.24183633,
                "energy_yield": 2.0857601991512347
            },
            {
                "name": "16",
                "installed_capacity_dc": 490.01705999999996,
                "land_area": 1036384.24183633,
                "energy_yield": 2.0336355662003753
            },
            {
                "name": "17",
                "installed_capacity_dc": 437.5404,
                "land_area": 1036384.24183633,
                "energy_yield": 2.1058031330482985
            },
            {
                "name": "18",
                "installed_capacity_dc": 507.50928,
                "land_area": 1036384.24183633,
                "energy_yield": 2.0040827384511672
            },
            {
                "name": "19",
                "installed_capacity_dc": 525.0015,
                "land_area": 1036384.24183633,
                "energy_yield": 1.972821217435862
            },
            {
                "name": "20",
                "installed_capacity_dc": 472.52484,
                "land_area": 1024538.1128490904,
                "energy_yield": 2.031529103865509
            },
            {
                "name": "21",
                "installed_capacity_dc": 455.03261999999995,
                "land_area": 1024538.1128490904,
                "energy_yield": 2.0556813432663357
            },
            {
                "name": "22",
                "installed_capacity_dc": 490.01705999999996,
                "land_area": 1024538.1128490904,
                "energy_yield": 2.0043510184248636
            },
            {
                "name": "23",
                "installed_capacity_dc": 437.5404,
                "land_area": 1024538.1128490904,
                "energy_yield": 2.0751928798340766
            },
            {
                "name": "24",
                "installed_capacity_dc": 507.50928,
                "land_area": 1024538.1128490904,
                "energy_yield": 1.9751800442064993
            },
            {
                "name": "25",
                "installed_capacity_dc": 455.03261999999995,
                "land_area": 1013182.866303615,
                "energy_yield": 2.026695427082825
            },
            {
                "name": "26",
                "installed_capacity_dc": 472.52484,
                "land_area": 1013182.866303615,
                "energy_yield": 2.0030163167550823
            },
            {
                "name": "27",
                "installed_capacity_dc": 525.0015,
                "land_area": 1024538.1128490904,
                "energy_yield": 1.9443971619921194
            },
            {
                "name": "28",
                "installed_capacity_dc": 437.5404,
                "land_area": 1013182.866303615,
                "energy_yield": 2.0456817797933855
            },
            {
                "name": "29",
                "installed_capacity_dc": 490.01705999999996,
                "land_area": 1013182.866303615,
                "energy_yield": 1.9762877663606275
            },
            {
                "name": "30",
                "installed_capacity_dc": 507.50928,
                "land_area": 1013182.866303615,
                "energy_yield": 1.9476662573074286
            },
            {
                "name": "31",
                "installed_capacity_dc": 525.0015,
                "land_area": 1013182.866303615,
                "energy_yield": 1.9174833655437984
            }
        ],
        "5031": [
            {
                "name": "2",
                "installed_capacity_dc": 584.99415,
                "land_area": 1062522.6558257374,
                "energy_yield": 2.1511041168937193
            },
            {
                "name": "3",
                "installed_capacity_dc": 607.493925,
                "land_area": 1062522.6558257374,
                "energy_yield": 2.1257151156764427
            },
            {
                "name": "4",
                "installed_capacity_dc": 562.494375,
                "land_area": 1062522.6558257374,
                "energy_yield": 2.1727303499966246
            },
            {
                "name": "5",
                "installed_capacity_dc": 629.9937,
                "land_area": 1062522.6558257374,
                "energy_yield": 2.0976198226833827
            },
            {
                "name": "6",
                "installed_capacity_dc": 584.99415,
                "land_area": 1054114.4755863403,
                "energy_yield": 2.1267980789683407
            },
            {
                "name": "7",
                "installed_capacity_dc": 607.493925,
                "land_area": 1054114.4755863403,
                "energy_yield": 2.101807568246776
            },
            {
                "name": "8",
                "installed_capacity_dc": 562.494375,
                "land_area": 1054114.4755863403,
                "energy_yield": 2.1479365295453614
            },
            {
                "name": "9",
                "installed_capacity_dc": 652.493475,
                "land_area": 1062522.6558257374,
                "energy_yield": 2.066898042867895
            },
            {
                "name": "10",
                "installed_capacity_dc": 629.9937,
                "land_area": 1054114.4755863403,
                "energy_yield": 2.074113109946195
            },
            {
                "name": "11",
                "installed_capacity_dc": 652.493475,
                "land_area": 1054114.4755863403,
                "energy_yield": 2.0437928653222097
            },
            {
                "name": "12",
                "installed_capacity_dc": 674.99325,
                "land_area": 1062522.6558257374,
                "energy_yield": 2.0347414632713523
            },
            {
                "name": "13",
                "installed_capacity_dc": 584.99415,
                "land_area": 1043373.54395701,
                "energy_yield": 2.098030712507847
            },
            {
                "name": "14",
                "installed_capacity_dc": 562.494375,
                "land_area": 1043373.54395701,
                "energy_yield": 2.118655274214454
            },
            {
                "name": "15",
                "installed_capacity_dc": 607.493925,
                "land_area": 1043373.54395701,
                "energy_yield": 2.0734349868924773
            },
            {
                "name": "16",
                "installed_capacity_dc": 629.9937,
                "land_area": 1043373.54395701,
                "energy_yield": 2.046167300870187
            },
            {
                "name": "17",
                "installed_capacity_dc": 674.99325,
                "land_area": 1054114.4755863403,
                "energy_yield": 2.01193444352494
            },
            {
                "name": "18",
                "installed_capacity_dc": 652.493475,
                "land_area": 1043373.54395701,
                "energy_yield": 2.0162520448336814
            },
            {
                "name": "19",
                "installed_capacity_dc": 584.99415,
                "land_area": 1031599.8495688213,
                "energy_yield": 2.0680856611489107
            },
            {
                "name": "20",
                "installed_capacity_dc": 562.494375,
                "land_area": 1031599.8495688213,
                "energy_yield": 2.0882360342696336
            },
            {
                "name": "21",
                "installed_capacity_dc": 607.493925,
                "land_area": 1031599.8495688213,
                "energy_yield": 2.0438542718377817
            },
            {
                "name": "22",
                "installed_capacity_dc": 629.9937,
                "land_area": 1031599.8495688213,
                "energy_yield": 2.016989484715387
            },
            {
                "name": "23",
                "installed_capacity_dc": 674.99325,
                "land_area": 1043373.54395701,
                "energy_yield": 1.9846968843276833
            },
            {
                "name": "24",
                "installed_capacity_dc": 652.493475,
                "land_area": 1031599.8495688213,
                "energy_yield": 1.9874887895920168
            },
            {
                "name": "25",
                "installed_capacity_dc": 584.99415,
                "land_area": 1020046.6482135109,
                "energy_yield": 2.0386885161556996
            },
            {
                "name": "26",
                "installed_capacity_dc": 562.494375,
                "land_area": 1020046.6482135109,
                "energy_yield": 2.0583342757767054
            },
            {
                "name": "27",
                "installed_capacity_dc": 607.493925,
                "land_area": 1020046.6482135109,
                "energy_yield": 2.014862690543076
            },
            {
                "name": "28",
                "installed_capacity_dc": 629.9937,
                "land_area": 1020046.6482135109,
                "energy_yield": 1.9884567061435474
            },
            {
                "name": "29",
                "installed_capacity_dc": 674.99325,
                "land_area": 1031599.8495688213,
                "energy_yield": 1.956331947139167
            },
            {
                "name": "30",
                "installed_capacity_dc": 652.493475,
                "land_area": 1020046.6482135109,
                "energy_yield": 1.9594858723192525
            },
            {
                "name": "31",
                "installed_capacity_dc": 674.99325,
                "land_area": 1020046.6482135109,
                "energy_yield": 1.9289148919666572
            }
        ],
        "30655": [
            {
                "name": "2",
                "installed_capacity_dc": 269.99154,
                "land_area": 880066.0757349968,
                "energy_yield": 1.8267961348301243
            },
            {
                "name": "3",
                "installed_capacity_dc": 259.99974,
                "land_area": 880066.0757349968,
                "energy_yield": 1.8421844415330146
            },
            {
                "name": "4",
                "installed_capacity_dc": 269.99154,
                "land_area": 885604.4957937121,
                "energy_yield": 1.8461908803855118
            },
            {
                "name": "5",
                "installed_capacity_dc": 259.99974,
                "land_area": 885604.4957937121,
                "energy_yield": 1.862017722422945
            },
            {
                "name": "6",
                "installed_capacity_dc": 279.98334,
                "land_area": 880066.0757349968,
                "energy_yield": 1.8076255687809781
            },
            {
                "name": "7",
                "installed_capacity_dc": 269.99154,
                "land_area": 873415.5383859229,
                "energy_yield": 1.8057946034491443
            },
            {
                "name": "8",
                "installed_capacity_dc": 259.99974,
                "land_area": 873415.5383859229,
                "energy_yield": 1.8207769506841947
            },
            {
                "name": "9",
                "installed_capacity_dc": 250.00794,
                "land_area": 880066.0757349968,
                "energy_yield": 1.852240804464996
            },
            {
                "name": "10",
                "installed_capacity_dc": 279.98334,
                "land_area": 885604.4957937121,
                "energy_yield": 1.8266008613861322
            },
            {
                "name": "11",
                "installed_capacity_dc": 279.98334,
                "land_area": 873415.5383859229,
                "energy_yield": 1.787035496640069
            },
            {
                "name": "12",
                "installed_capacity_dc": 250.00794,
                "land_area": 885604.4957937121,
                "energy_yield": 1.8724756905528903
            },
            {
                "name": "13",
                "installed_capacity_dc": 289.97514,
                "land_area": 880066.0757349968,
                "energy_yield": 1.7856828284541149
            },
            {
                "name": "14",
                "installed_capacity_dc": 250.00794,
                "land_area": 873415.5383859229,
                "energy_yield": 1.8304541830159429
            },
            {
                "name": "15",
                "installed_capacity_dc": 269.99154,
                "land_area": 865763.5070696505,
                "energy_yield": 1.7831519513553329
            },
            {
                "name": "16",
                "installed_capacity_dc": 259.99974,
                "land_area": 865763.5070696505,
                "energy_yield": 1.7977194938606544
            },
            {
                "name": "17",
                "installed_capacity_dc": 289.97514,
                "land_area": 873415.5383859229,
                "energy_yield": 1.7655286671398809
            },
            {
                "name": "18",
                "installed_capacity_dc": 289.97514,
                "land_area": 885604.4957937121,
                "energy_yield": 1.8041731545044801
            },
            {
                "name": "19",
                "installed_capacity_dc": 279.98334,
                "land_area": 865763.5070696505,
                "energy_yield": 1.7648430805924737
            },
            {
                "name": "20",
                "installed_capacity_dc": 250.00794,
                "land_area": 865763.5070696505,
                "energy_yield": 1.8070441675176128
            },
            {
                "name": "21",
                "installed_capacity_dc": 299.96693999999997,
                "land_area": 880066.0757349968,
                "energy_yield": 1.7613366295525652
            },
            {
                "name": "22",
                "installed_capacity_dc": 289.97514,
                "land_area": 865763.5070696505,
                "energy_yield": 1.7437673363661395
            },
            {
                "name": "23",
                "installed_capacity_dc": 299.96693999999997,
                "land_area": 873415.5383859229,
                "energy_yield": 1.7415707536890659
            },
            {
                "name": "24",
                "installed_capacity_dc": 269.99154,
                "land_area": 856775.4279363794,
                "energy_yield": 1.7593156642471404
            },
            {
                "name": "25",
                "installed_capacity_dc": 299.96693999999997,
                "land_area": 885604.4957937121,
                "energy_yield": 1.7794765677930442
            },
            {
                "name": "26",
                "installed_capacity_dc": 259.99974,
                "land_area": 856775.4279363794,
                "energy_yield": 1.7734607550692127
            },
            {
                "name": "27",
                "installed_capacity_dc": 279.98334,
                "land_area": 856775.4279363794,
                "energy_yield": 1.741453568924153
            },
            {
                "name": "28",
                "installed_capacity_dc": 250.00794,
                "land_area": 856775.4279363794,
                "energy_yield": 1.7824544720679278
            },
            {
                "name": "29",
                "installed_capacity_dc": 299.96693999999997,
                "land_area": 865763.5070696505,
                "energy_yield": 1.720307180824751
            },
            {
                "name": "30",
                "installed_capacity_dc": 289.97514,
                "land_area": 856775.4279363794,
                "energy_yield": 1.720838118269044
            },
            {
                "name": "31",
                "installed_capacity_dc": 299.96693999999997,
                "land_area": 856775.4279363794,
                "energy_yield": 1.6979519994966834
            }
        ],
        "5416": [
            {
                "name": "2",
                "installed_capacity_dc": 130.9568,
                "land_area": 407035.28661822114,
                "energy_yield": 0.8313224535382893
            },
            {
                "name": "3",
                "installed_capacity_dc": 141.57312,
                "land_area": 407035.28661822114,
                "energy_yield": 0.8040260552494047
            },
            {
                "name": "4",
                "installed_capacity_dc": 120.19072,
                "land_area": 407035.28661822114,
                "energy_yield": 0.853985898309333
            },
            {
                "name": "5",
                "installed_capacity_dc": 152.35584,
                "land_area": 407035.28661822114,
                "energy_yield": 0.7763100835897621
            },
            {
                "name": "6",
                "installed_capacity_dc": 108.6592,
                "land_area": 407035.28661822114,
                "energy_yield": 0.8728183194857624
            },
            {
                "name": "7",
                "installed_capacity_dc": 98.32576,
                "land_area": 407035.28661822114,
                "energy_yield": 0.8876042424167864
            },
            {
                "name": "8",
                "installed_capacity_dc": 162.4064,
                "land_area": 407035.28661822114,
                "energy_yield": 0.7441266338786302
            },
            {
                "name": "9",
                "installed_capacity_dc": 87.75936,
                "land_area": 407035.28661822114,
                "energy_yield": 0.8970278851326215
            },
            {
                "name": "10",
                "installed_capacity_dc": 173.82144,
                "land_area": 407035.28661822114,
                "energy_yield": 0.7132213966178653
            },
            {
                "name": "11",
                "installed_capacity_dc": 76.72704,
                "land_area": 407035.28661822114,
                "energy_yield": 0.9047296192339787
            },
            {
                "name": "12",
                "installed_capacity_dc": 65.52832,
                "land_area": 407035.28661822114,
                "energy_yield": 0.9070017436025437
            }
        ]
    }
}